walytis_beta_api/__init__.py
walytis_beta_api/__main__.py
walytis_beta_api/block_model.py
walytis_beta_api/blockchain_model.py
walytis_beta_api/exceptions.py
walytis_beta_api/versions.py
walytis_beta_api/walytis_beta_brenthy_api.py
walytis_beta_api/walytis_beta_embedded_api.py
walytis_beta_api/walytis_beta_generic_interface.py
walytis_beta_api/walytis_beta_interface.py
walytis_beta_api/_experimental/__init__.py
walytis_beta_api/_experimental/generic_blockchain.py
walytis_beta_api/_experimental/generic_blockchain_testing.py
walytis_beta_tools/__init__.py
walytis_beta_tools/block_model.py
walytis_beta_tools/exceptions.py
walytis_beta_tools/log.py
walytis_beta_tools/versions.py
walytis_beta_tools/_experimental/__init__.py
walytis_beta_tools/_experimental/block_lazy_loading.py
walytis_beta_tools/_experimental/config.py
walytis_beta_tools/_experimental/generic_block.py
walytis_beta_tools/_experimental/ipfs_interface.py
walytis_beta_api-2.4.16.dist-info/METADATA
walytis_beta_api-2.4.16.dist-info/WHEEL
walytis_beta_api-2.4.16.dist-info/top_level.txt
walytis_beta_api-2.4.16.dist-info/RECORD
